[
  {
    "name": "Aniyomi: Art Lapsa",
    "pkg": "eu.kanade.tachiyomi.extension.en.artlapsa",
    "apk": "aniyomi-en.artlapsa-v1.4.21.apk",
    "lang": "en",
    "code": 21,
    "version": "1.4.21",
    "nsfw": 0,
    "sources": [
      {
        "name": "Art Lapsa",
        "lang": "en",
        "id": "734404203508686053",
        "baseUrl": "https://artlapsa.com",
        "versionId": 1
      }
    ]
  },
  {
    "name": "Aniyomi: RitharScans",
    "pkg": "eu.kanade.tachiyomi.extension.en.ritharscans",
    "apk": "aniyomi-en.ritharscans-v1.4.20.apk",
    "lang": "en",
    "code": 20,
    "version": "1.4.20",
    "nsfw": 0,
    "sources": [
      {
        "name": "RitharScans",
        "lang": "en",
        "id": "8220771912098311271",
        "baseUrl": "https://ritharscans.com",
        "versionId": 1
      }
    ]
  }
]